design.v
module half_adder_scan (
    input  clk,
    input  rst_n,

    input  a_in,
    input  b_in,

    input  scan_en,
    input  scan_in,
    output scan_out,

    output sum,
    output carry
);

  reg a_ff, b_ff;

  always @(posedge clk or negedge rst_n) begin
    if (!rst_n) begin
      a_ff <= 1'b0;
      b_ff <= 1'b0;
    end else if (scan_en) begin
      a_ff <= scan_in;
      b_ff <= a_ff;
    end else begin
      a_ff <= a_in;
      b_ff <= b_in;
    end
  end

  assign scan_out = b_ff;

  assign sum   = a_ff ^ b_ff;
  assign carry = a_ff & b_ff;

endmodule

tb.v
`timescale 1ns/1ps

module half_adder_scan_tb;

  reg clk;
  reg rst_n;

  reg a_in, b_in;
  reg scan_en, scan_in;

  wire scan_out;
  wire sum, carry;

  half_adder_scan dut (
    .clk(clk),
    .rst_n(rst_n),
    .a_in(a_in),
    .b_in(b_in),
    .scan_en(scan_en),
    .scan_in(scan_in),
    .scan_out(scan_out),
    .sum(sum),
    .carry(carry)
  );

  always #5 clk = ~clk;

  initial begin
    $dumpfile("half_adder_scan.vcd");
    $dumpvars(0, half_adder_scan_tb);

    clk     = 0;
    rst_n   = 0;
    a_in    = 0;
    b_in    = 0;
    scan_en = 0;
    scan_in = 0;

    #12;
    rst_n = 1;


    scan_en = 1;

    scan_in = 1;  
    #10;

    scan_in = 0;  
    #10;

    scan_en = 0;

    #20;


    a_in = 0; b_in = 0; #10;
    a_in = 0; b_in = 1; #10;
    a_in = 1; b_in = 0; #10;
    a_in = 1; b_in = 1; #10;

    #20;
    $finish;
  end

endmodule

waveform.vcd
$date
	Mon Jan 26 22:56:43 2026
$end
$version
	Icarus Verilog
$end
$timescale
	1ps
$end
$scope module half_adder_scan_tb $end
$var wire 1 ! sum $end
$var wire 1 " scan_out $end
$var wire 1 # carry $end
$var reg 1 $ a_in $end
$var reg 1 % b_in $end
$var reg 1 & clk $end
$var reg 1 ' rst_n $end
$var reg 1 ( scan_en $end
$var reg 1 ) scan_in $end
$scope module dut $end
$var wire 1 $ a_in $end
$var wire 1 % b_in $end
$var wire 1 # carry $end
$var wire 1 & clk $end
$var wire 1 ' rst_n $end
$var wire 1 ( scan_en $end
$var wire 1 ) scan_in $end
$var wire 1 " scan_out $end
$var wire 1 ! sum $end
$var reg 1 * a_ff $end
$var reg 1 + b_ff $end
$upscope $end
$upscope $end
$enddefinitions $end
$comment Show the parameter values. $end
$dumpall
$end
#0
$dumpvars
0+
0*
0)
0(
0'
0&
0%
0$
0#
0"
0!
$end
#5000
1&
#10000
0&
#12000
1)
1(
1'
#15000
1!
1*
1&
#20000
0&
#22000
0)
#25000
1"
1+
0*
1&
#30000
0&
#32000
0(
#35000
0!
0"
0+
1&
#40000
0&
#45000
1&
#50000
0&
#55000
1&
#60000
0&
#62000
1%
#65000
1!
1"
1+
1&
#70000
0&
#72000
0%
1$
#75000
0"
0+
1*
1&
#80000
0&
#82000
1%
#85000
1#
0!
1"
1+
1&
